soe.py
soe-0.0.6.dist-info/WHEEL
soe-0.0.6.dist-info/METADATA
soe-0.0.6.dist-info/RECORD
