Metadata-Version: 2.1
Name: soe
Version: 0.0.6
Summary: This library is needed to manage the operating system. It contains the functions of the os, sys, psutil module.
Author: Vova
Author-email: vovahat09@gmail.com
Requires-Python: >=3.7,<4.0
Classifier: Programming Language :: Python :: 3
Classifier: Programming Language :: Python :: 3.7
Classifier: Programming Language :: Python :: 3.8
Classifier: Programming Language :: Python :: 3.9
